obsidian_to_hugo/__init__.py
obsidian_to_hugo/__main__.py
obsidian_to_hugo/md_mark_processor.py
obsidian_to_hugo/obsidian_to_hugo.py
obsidian_to_hugo/wiki_links_processor.py
obsidian_to_hugo-12023.3.21.dist-info/LICENSE
obsidian_to_hugo-12023.3.21.dist-info/METADATA
obsidian_to_hugo-12023.3.21.dist-info/WHEEL
obsidian_to_hugo-12023.3.21.dist-info/top_level.txt
obsidian_to_hugo-12023.3.21.dist-info/RECORD
