Metadata-Version: 2.1
Name: obsidian-to-hugo
Version: 12023.3.21
Summary: Process Obsidian notes to publish them with Hugo. Transforms Obsidian wiki links into Hugo shortcodes for internal linking.
Author-email: David Wolf <d@wolf.gdn>
License: MIT
Project-URL: Source, https://github.com/devidw/obsidian-to-hugo
Project-URL: Bug Tracker, https://github.com/devidw/obsidian-to-hugo/issues
Keywords: obsidian,hugo,markdown,wikilink
Classifier: Typing :: Typed
Classifier: Environment :: Console
Classifier: License :: OSI Approved :: MIT License
Classifier: Operating System :: OS Independent
Classifier: Programming Language :: Python :: 3
Classifier: Topic :: Text Processing :: Markup
Requires-Python: >=3.6
License-File: LICENSE
